bismuth_coverage/__about__.py
bismuth_coverage/__init__.py
bismuth_coverage-0.0.1.dist-info/METADATA
bismuth_coverage-0.0.1.dist-info/WHEEL
bismuth_coverage-0.0.1.dist-info/licenses/LICENSE.txt
bismuth_coverage-0.0.1.dist-info/RECORD
